pdsearch/__init__.py
pdsearch-0.1.0.dist-info/WHEEL
pdsearch-0.1.0.dist-info/METADATA
pdsearch-0.1.0.dist-info/RECORD
