Metadata-Version: 2.1
Name: pdsearch
Version: 0.1.0
Summary: Let's find some podcasts!
Home-page: https://github.com/unuuunu/pod-search
Author: unuuunu
Author-email: 000llj7@gmail.com
Classifier: License :: OSI Approved :: MIT License
